{
    "id": 140079125,
    "name": "nie tak tak tak tak",
    "author": "Pingas23",
    "creators": ["Pingas23"],
    "verifier": "Specie",
    "verification": "https://youtu.be/IIT3z-RCFBc",
    "percentToQualify": 56,
    "password": "None",
    "enjoyment": "0/10",
    "description": "NONG: https://cdn.discordapp.com/attachments/1386460976831795221/1503029749218410678/Mne_tak_tak_tak_slowed_reverb_niche_larp.mp3?ex=6a300189&is=6a2eb009&hm=dc0add7d2668413bbccf4d0ecd40dd2dd8c6121194877e1087352c6014029f09&",
    "records": [
        {
            "user": "gopsolaptop",
            "link": "https://youtu.be/V4115ZDMrwY?t=846",
            "percent": 100,
            "hz": 240
        }
    ]
}
